[
    {
      "Rank": 1,
      "Name": "Alex Lépine",
      "PJ": 1568,
      "PTS": 1698,
      "BTS": 373,
      "PAS": 535,
      "VIC": 66,
      "DP": 9,
      "BL": 12,
      "Ratio": 83,
      "PUN": 637,
      "SAL": "90,372",
      "ECM": 132,
      "EC": 0
    },
    {
      "Rank": 2,
      "Name": "Mathieu Gravel",
      "PJ": 1509,
      "PTS": 1683,
      "BTS": 322,
      "PAS": 599,
      "VIC": 59,
      "DP": 7,
      "BL": 10,
      "Ratio": 30,
      "PUN": 470,
      "SAL": "101,933",
      "ECM": 117,
      "EC": 15
    },
    {
      "Rank": 3,
      "Name": "Jean-Christophe M.",
      "PJ": 1556,
      "PTS": 1666,
      "BTS": 367,
      "PAS": 525,
      "VIC": 67,
      "DP": 17,
      "BL": 13,
      "Ratio": -59,
      "PUN": 606,
      "SAL": "74,796",
      "ECM": 100,
      "EC": 32
    },
    {
      "Rank": 4,
      "Name": "Alexandre Bourgeois",
      "PJ": 1534,
      "PTS": 1606,
      "BTS": 345,
      "PAS": 548,
      "VIC": 54,
      "DP": 11,
      "BL": 4,
      "Ratio": -22,
      "PUN": 491,
      "SAL": "67,211",
      "ECM": 40,
      "EC": 92
    },
    {
      "Rank": 5,
      "Name": "Éric Chalut",
      "PJ": 1615,
      "PTS": 1583,
      "BTS": 278,
      "PAS": 591,
      "VIC": 59,
      "DP": 11,
      "BL": 4,
      "Ratio": -115,
      "PUN": 772,
      "SAL": "115,161",
      "ECM": 17,
      "EC": 115
    },
    {
      "Rank": 6,
      "Name": "Mohamed B.Bouchta",
      "PJ": 1579,
      "PTS": 1550,
      "BTS": 280,
      "PAS": 602,
      "VIC": 41,
      "DP": 19,
      "BL": 3,
      "Ratio": 79,
      "PUN": 727,
      "SAL": "103,416",
      "ECM": -15,
      "EC": 148
    },
    {
      "Rank": 7,
      "Name": "Sébastien Morneau",
      "PJ": 1555,
      "PTS": 1491,
      "BTS": 281,
      "PAS": 525,
      "VIC": 49,
      "DP": 9,
      "BL": 3,
      "Ratio": -95,
      "PUN": 637,
      "SAL": "98,165",
      "ECM": -74,
      "EC": 207
    },
    {
      "Rank": 8,
      "Name": "Jessica Trottier",
      "PJ": 1428,
      "PTS": 1490,
      "BTS": 296,
      "PAS": 527,
      "VIC": 68,
      "DP": 14,
      "BL": 11,
      "Ratio": 106,
      "PUN": 649,
      "SAL": "91,040",
      "ECM": -75,
      "EC": 208
    },
    {
      "Rank": 9,
      "Name": "Maxime Lépine",
      "PJ": 1528,
      "PTS": 1468,
      "BTS": 333,
      "PAS": 461,
      "VIC": 51,
      "DP": 14,
      "BL": 5,
      "Ratio": -7,
      "PUN": 597,
      "SAL": "103,138",
      "ECM": -97,
      "EC": 230
    },
    {
      "Rank": 10,
      "Name": "Emma-Genevieve M. STL",
      "PJ": 1491,
      "PTS": 1418,
      "BTS": 239,
      "PAS": 499,
      "VIC": 77,
      "DP": 12,
      "BL": 11,
      "Ratio": 53,
      "PUN": 574,
      "SAL": "104,315",
      "ECM": -147,
      "EC": 28
    }
   ]